{
    "total": 3040,
    "total_pages": 304,
    "results": [
        {
            "id": "NflJmUuaYVI",
            "created_at": "2020-10-15T18:26:07-04:00",
            "updated_at": "2021-11-12T05:21:36-05:00",
            "promoted_at": null,
            "width": 5100,
            "height": 3400,
            "color": "#737373",
            "blur_hash": "LREf+-kBo}V[cIt7ozR%k?fhkCWC",
            "description": "Daybreak over downtown Denver with a view of the Rocky Mountains to the west",
            "alt_description": "aerial view of city buildings during daytime",
            "urls": {
                "raw": "https://images.unsplash.com/photo-1602800458591-eddda28a498b?ixid=MnwyNzUyNDB8MHwxfHNlYXJjaHwxfHxkZW52ZXJ8ZW58MHx8fHwxNjM2Nzc5NzY2&ixlib=rb-1.2.1",
                "full": "https://images.unsplash.com/photo-1602800458591-eddda28a498b?crop=entropy&cs=srgb&fm=jpg&ixid=MnwyNzUyNDB8MHwxfHNlYXJjaHwxfHxkZW52ZXJ8ZW58MHx8fHwxNjM2Nzc5NzY2&ixlib=rb-1.2.1&q=85",
                "regular": "https://images.unsplash.com/photo-1602800458591-eddda28a498b?crop=entropy&cs=tinysrgb&fit=max&fm=jpg&ixid=MnwyNzUyNDB8MHwxfHNlYXJjaHwxfHxkZW52ZXJ8ZW58MHx8fHwxNjM2Nzc5NzY2&ixlib=rb-1.2.1&q=80&w=1080",
                "small": "https://images.unsplash.com/photo-1602800458591-eddda28a498b?crop=entropy&cs=tinysrgb&fit=max&fm=jpg&ixid=MnwyNzUyNDB8MHwxfHNlYXJjaHwxfHxkZW52ZXJ8ZW58MHx8fHwxNjM2Nzc5NzY2&ixlib=rb-1.2.1&q=80&w=400",
                "thumb": "https://images.unsplash.com/photo-1602800458591-eddda28a498b?crop=entropy&cs=tinysrgb&fit=max&fm=jpg&ixid=MnwyNzUyNDB8MHwxfHNlYXJjaHwxfHxkZW52ZXJ8ZW58MHx8fHwxNjM2Nzc5NzY2&ixlib=rb-1.2.1&q=80&w=200"
            },
            "links": {
                "self": "https://api.unsplash.com/photos/NflJmUuaYVI",
                "html": "https://unsplash.com/photos/NflJmUuaYVI",
                "download": "https://unsplash.com/photos/NflJmUuaYVI/download?ixid=MnwyNzUyNDB8MHwxfHNlYXJjaHwxfHxkZW52ZXJ8ZW58MHx8fHwxNjM2Nzc5NzY2",
                "download_location": "https://api.unsplash.com/photos/NflJmUuaYVI/download?ixid=MnwyNzUyNDB8MHwxfHNlYXJjaHwxfHxkZW52ZXJ8ZW58MHx8fHwxNjM2Nzc5NzY2"
            },
            "categories": [],
            "likes": 23,
            "liked_by_user": false,
            "current_user_collections": [],
            "sponsorship": null,
            "topic_submissions": {},
            "user": {
                "id": "iReUjmhpLcw",
                "updated_at": "2021-11-12T08:29:10-05:00",
                "username": "andrewcoop",
                "name": "Andrew Coop",
                "first_name": "Andrew",
                "last_name": "Coop",
                "twitter_username": null,
                "portfolio_url": null,
                "bio": "I'm an amateur who likes to shoot just about everything that looks interesting.  I want to get more experience with portraiture, and will shoot personal photos for anyone for free.  Where possible, attribution is appreciated please and thank you.",
                "location": "Aurora, CO, USA",
                "links": {
                    "self": "https://api.unsplash.com/users/andrewcoop",
                    "html": "https://unsplash.com/@andrewcoop",
                    "photos": "https://api.unsplash.com/users/andrewcoop/photos",
                    "likes": "https://api.unsplash.com/users/andrewcoop/likes",
                    "portfolio": "https://api.unsplash.com/users/andrewcoop/portfolio",
                    "following": "https://api.unsplash.com/users/andrewcoop/following",
                    "followers": "https://api.unsplash.com/users/andrewcoop/followers"
                },
                "profile_image": {
                    "small": "https://images.unsplash.com/profile-1623106766393-2f16aecfe7b9image?ixlib=rb-1.2.1&q=80&fm=jpg&crop=faces&cs=tinysrgb&fit=crop&h=32&w=32",
                    "medium": "https://images.unsplash.com/profile-1623106766393-2f16aecfe7b9image?ixlib=rb-1.2.1&q=80&fm=jpg&crop=faces&cs=tinysrgb&fit=crop&h=64&w=64",
                    "large": "https://images.unsplash.com/profile-1623106766393-2f16aecfe7b9image?ixlib=rb-1.2.1&q=80&fm=jpg&crop=faces&cs=tinysrgb&fit=crop&h=128&w=128"
                },
                "instagram_username": null,
                "total_collections": 0,
                "total_likes": 36,
                "total_photos": 296,
                "accepted_tos": true,
                "for_hire": true,
                "social": {
                    "instagram_username": null,
                    "portfolio_url": null,
                    "twitter_username": null,
                    "paypal_email": null
                }
            },
            "tags": [
                {
                    "type": "search",
                    "title": "denver"
                },
                {
                    "type": "search",
                    "title": "co"
                },
                {
                    "type": "search",
                    "title": "usa"
                }
            ]
        },
        {
            "id": "r82eni3j0bI",
            "created_at": "2020-09-06T12:05:36-04:00",
            "updated_at": "2021-11-12T15:18:58-05:00",
            "promoted_at": null,
            "width": 4862,
            "height": 3646,
            "color": "#0c59c0",
            "blur_hash": "LhC*9MtlR*V@KUazoekCIwWYaKa#",
            "description": "Downtown Denver and Capitol Building",
            "alt_description": "white and gold dome building",
            "urls": {
                "raw": "https://images.unsplash.com/photo-1599408169542-620fc453382c?ixid=MnwyNzUyNDB8MHwxfHNlYXJjaHwyfHxkZW52ZXJ8ZW58MHx8fHwxNjM2Nzc5NzY2&ixlib=rb-1.2.1",
                "full": "https://images.unsplash.com/photo-1599408169542-620fc453382c?crop=entropy&cs=srgb&fm=jpg&ixid=MnwyNzUyNDB8MHwxfHNlYXJjaHwyfHxkZW52ZXJ8ZW58MHx8fHwxNjM2Nzc5NzY2&ixlib=rb-1.2.1&q=85",
                "regular": "https://images.unsplash.com/photo-1599408169542-620fc453382c?crop=entropy&cs=tinysrgb&fit=max&fm=jpg&ixid=MnwyNzUyNDB8MHwxfHNlYXJjaHwyfHxkZW52ZXJ8ZW58MHx8fHwxNjM2Nzc5NzY2&ixlib=rb-1.2.1&q=80&w=1080",
                "small": "https://images.unsplash.com/photo-1599408169542-620fc453382c?crop=entropy&cs=tinysrgb&fit=max&fm=jpg&ixid=MnwyNzUyNDB8MHwxfHNlYXJjaHwyfHxkZW52ZXJ8ZW58MHx8fHwxNjM2Nzc5NzY2&ixlib=rb-1.2.1&q=80&w=400",
                "thumb": "https://images.unsplash.com/photo-1599408169542-620fc453382c?crop=entropy&cs=tinysrgb&fit=max&fm=jpg&ixid=MnwyNzUyNDB8MHwxfHNlYXJjaHwyfHxkZW52ZXJ8ZW58MHx8fHwxNjM2Nzc5NzY2&ixlib=rb-1.2.1&q=80&w=200"
            },
            "links": {
                "self": "https://api.unsplash.com/photos/r82eni3j0bI",
                "html": "https://unsplash.com/photos/r82eni3j0bI",
                "download": "https://unsplash.com/photos/r82eni3j0bI/download?ixid=MnwyNzUyNDB8MHwxfHNlYXJjaHwyfHxkZW52ZXJ8ZW58MHx8fHwxNjM2Nzc5NzY2",
                "download_location": "https://api.unsplash.com/photos/r82eni3j0bI/download?ixid=MnwyNzUyNDB8MHwxfHNlYXJjaHwyfHxkZW52ZXJ8ZW58MHx8fHwxNjM2Nzc5NzY2"
            },
            "categories": [],
            "likes": 21,
            "liked_by_user": false,
            "current_user_collections": [],
            "sponsorship": null,
            "topic_submissions": {},
            "user": {
                "id": "iReUjmhpLcw",
                "updated_at": "2021-11-12T08:29:10-05:00",
                "username": "andrewcoop",
                "name": "Andrew Coop",
                "first_name": "Andrew",
                "last_name": "Coop",
                "twitter_username": null,
                "portfolio_url": null,
                "bio": "I'm an amateur who likes to shoot just about everything that looks interesting.  I want to get more experience with portraiture, and will shoot personal photos for anyone for free.  Where possible, attribution is appreciated please and thank you.",
                "location": "Aurora, CO, USA",
                "links": {
                    "self": "https://api.unsplash.com/users/andrewcoop",
                    "html": "https://unsplash.com/@andrewcoop",
                    "photos": "https://api.unsplash.com/users/andrewcoop/photos",
                    "likes": "https://api.unsplash.com/users/andrewcoop/likes",
                    "portfolio": "https://api.unsplash.com/users/andrewcoop/portfolio",
                    "following": "https://api.unsplash.com/users/andrewcoop/following",
                    "followers": "https://api.unsplash.com/users/andrewcoop/followers"
                },
                "profile_image": {
                    "small": "https://images.unsplash.com/profile-1623106766393-2f16aecfe7b9image?ixlib=rb-1.2.1&q=80&fm=jpg&crop=faces&cs=tinysrgb&fit=crop&h=32&w=32",
                    "medium": "https://images.unsplash.com/profile-1623106766393-2f16aecfe7b9image?ixlib=rb-1.2.1&q=80&fm=jpg&crop=faces&cs=tinysrgb&fit=crop&h=64&w=64",
                    "large": "https://images.unsplash.com/profile-1623106766393-2f16aecfe7b9image?ixlib=rb-1.2.1&q=80&fm=jpg&crop=faces&cs=tinysrgb&fit=crop&h=128&w=128"
                },
                "instagram_username": null,
                "total_collections": 0,
                "total_likes": 36,
                "total_photos": 296,
                "accepted_tos": true,
                "for_hire": true,
                "social": {
                    "instagram_username": null,
                    "portfolio_url": null,
                    "twitter_username": null,
                    "paypal_email": null
                }
            },
            "tags": [
                {
                    "type": "search",
                    "title": "denver"
                },
                {
                    "type": "search",
                    "title": "co"
                },
                {
                    "type": "search",
                    "title": "usa"
                }
            ]
        },
        {
            "id": "r6BdUpN_iSk",
            "created_at": "2019-11-09T06:07:11-05:00",
            "updated_at": "2021-11-12T14:12:53-05:00",
            "promoted_at": null,
            "width": 3913,
            "height": 2201,
            "color": "#0c2659",
            "blur_hash": "LKF$@hBnGF@]}]GYF=id#7n$jGPS",
            "description": null,
            "alt_description": "Denver street artowrk",
            "urls": {
                "raw": "https://images.unsplash.com/photo-1573297627466-6bed413a43f1?ixid=MnwyNzUyNDB8MHwxfHNlYXJjaHwzfHxkZW52ZXJ8ZW58MHx8fHwxNjM2Nzc5NzY2&ixlib=rb-1.2.1",
                "full": "https://images.unsplash.com/photo-1573297627466-6bed413a43f1?crop=entropy&cs=srgb&fm=jpg&ixid=MnwyNzUyNDB8MHwxfHNlYXJjaHwzfHxkZW52ZXJ8ZW58MHx8fHwxNjM2Nzc5NzY2&ixlib=rb-1.2.1&q=85",
                "regular": "https://images.unsplash.com/photo-1573297627466-6bed413a43f1?crop=entropy&cs=tinysrgb&fit=max&fm=jpg&ixid=MnwyNzUyNDB8MHwxfHNlYXJjaHwzfHxkZW52ZXJ8ZW58MHx8fHwxNjM2Nzc5NzY2&ixlib=rb-1.2.1&q=80&w=1080",
                "small": "https://images.unsplash.com/photo-1573297627466-6bed413a43f1?crop=entropy&cs=tinysrgb&fit=max&fm=jpg&ixid=MnwyNzUyNDB8MHwxfHNlYXJjaHwzfHxkZW52ZXJ8ZW58MHx8fHwxNjM2Nzc5NzY2&ixlib=rb-1.2.1&q=80&w=400",
                "thumb": "https://images.unsplash.com/photo-1573297627466-6bed413a43f1?crop=entropy&cs=tinysrgb&fit=max&fm=jpg&ixid=MnwyNzUyNDB8MHwxfHNlYXJjaHwzfHxkZW52ZXJ8ZW58MHx8fHwxNjM2Nzc5NzY2&ixlib=rb-1.2.1&q=80&w=200"
            },
            "links": {
                "self": "https://api.unsplash.com/photos/r6BdUpN_iSk",
                "html": "https://unsplash.com/photos/r6BdUpN_iSk",
                "download": "https://unsplash.com/photos/r6BdUpN_iSk/download?ixid=MnwyNzUyNDB8MHwxfHNlYXJjaHwzfHxkZW52ZXJ8ZW58MHx8fHwxNjM2Nzc5NzY2",
                "download_location": "https://api.unsplash.com/photos/r6BdUpN_iSk/download?ixid=MnwyNzUyNDB8MHwxfHNlYXJjaHwzfHxkZW52ZXJ8ZW58MHx8fHwxNjM2Nzc5NzY2"
            },
            "categories": [],
            "likes": 99,
            "liked_by_user": false,
            "current_user_collections": [],
            "sponsorship": null,
            "topic_submissions": {},
            "user": {
                "id": "_i9h5vnI7Dk",
                "updated_at": "2021-11-10T18:37:35-05:00",
                "username": "planner1963",
                "name": "Pieter van de Sande",
                "first_name": "Pieter",
                "last_name": "van de Sande",
                "twitter_username": "PieterKoolhoven",
                "portfolio_url": null,
                "bio": null,
                "location": null,
                "links": {
                    "self": "https://api.unsplash.com/users/planner1963",
                    "html": "https://unsplash.com/@planner1963",
                    "photos": "https://api.unsplash.com/users/planner1963/photos",
                    "likes": "https://api.unsplash.com/users/planner1963/likes",
                    "portfolio": "https://api.unsplash.com/users/planner1963/portfolio",
                    "following": "https://api.unsplash.com/users/planner1963/following",
                    "followers": "https://api.unsplash.com/users/planner1963/followers"
                },
                "profile_image": {
                    "small": "https://images.unsplash.com/profile-1571821634755-dfe07da83209image?ixlib=rb-1.2.1&q=80&fm=jpg&crop=faces&cs=tinysrgb&fit=crop&h=32&w=32",
                    "medium": "https://images.unsplash.com/profile-1571821634755-dfe07da83209image?ixlib=rb-1.2.1&q=80&fm=jpg&crop=faces&cs=tinysrgb&fit=crop&h=64&w=64",
                    "large": "https://images.unsplash.com/profile-1571821634755-dfe07da83209image?ixlib=rb-1.2.1&q=80&fm=jpg&crop=faces&cs=tinysrgb&fit=crop&h=128&w=128"
                },
                "instagram_username": "pietervandesandeme.com",
                "total_collections": 5,
                "total_likes": 100,
                "total_photos": 59,
                "accepted_tos": true,
                "for_hire": false,
                "social": {
                    "instagram_username": "pietervandesandeme.com",
                    "portfolio_url": null,
                    "twitter_username": "PieterKoolhoven",
                    "paypal_email": null
                }
            },
            "tags": [
                {
                    "type": "search",
                    "title": "denver"
                },
                {
                    "type": "search",
                    "title": "colorado"
                },
                {
                    "type": "search",
                    "title": "verenigde staten"
                }
            ]
        },
        {
            "id": "7C00d3z3ssU",
            "created_at": "2021-03-23T00:25:40-04:00",
            "updated_at": "2021-11-12T08:24:57-05:00",
            "promoted_at": null,
            "width": 4640,
            "height": 6960,
            "color": "#c0c0c0",
            "blur_hash": "LeF~jcs:M{jZ_NofRjj[D*kCWCof",
            "description": "instagram - @jakobnoahrosen",
            "alt_description": "city skyline during night time",
            "urls": {
                "raw": "https://images.unsplash.com/photo-1616473515087-d3ad3fe87a24?ixid=MnwyNzUyNDB8MHwxfHNlYXJjaHw0fHxkZW52ZXJ8ZW58MHx8fHwxNjM2Nzc5NzY2&ixlib=rb-1.2.1",
                "full": "https://images.unsplash.com/photo-1616473515087-d3ad3fe87a24?crop=entropy&cs=srgb&fm=jpg&ixid=MnwyNzUyNDB8MHwxfHNlYXJjaHw0fHxkZW52ZXJ8ZW58MHx8fHwxNjM2Nzc5NzY2&ixlib=rb-1.2.1&q=85",
                "regular": "https://images.unsplash.com/photo-1616473515087-d3ad3fe87a24?crop=entropy&cs=tinysrgb&fit=max&fm=jpg&ixid=MnwyNzUyNDB8MHwxfHNlYXJjaHw0fHxkZW52ZXJ8ZW58MHx8fHwxNjM2Nzc5NzY2&ixlib=rb-1.2.1&q=80&w=1080",
                "small": "https://images.unsplash.com/photo-1616473515087-d3ad3fe87a24?crop=entropy&cs=tinysrgb&fit=max&fm=jpg&ixid=MnwyNzUyNDB8MHwxfHNlYXJjaHw0fHxkZW52ZXJ8ZW58MHx8fHwxNjM2Nzc5NzY2&ixlib=rb-1.2.1&q=80&w=400",
                "thumb": "https://images.unsplash.com/photo-1616473515087-d3ad3fe87a24?crop=entropy&cs=tinysrgb&fit=max&fm=jpg&ixid=MnwyNzUyNDB8MHwxfHNlYXJjaHw0fHxkZW52ZXJ8ZW58MHx8fHwxNjM2Nzc5NzY2&ixlib=rb-1.2.1&q=80&w=200"
            },
            "links": {
                "self": "https://api.unsplash.com/photos/7C00d3z3ssU",
                "html": "https://unsplash.com/photos/7C00d3z3ssU",
                "download": "https://unsplash.com/photos/7C00d3z3ssU/download?ixid=MnwyNzUyNDB8MHwxfHNlYXJjaHw0fHxkZW52ZXJ8ZW58MHx8fHwxNjM2Nzc5NzY2",
                "download_location": "https://api.unsplash.com/photos/7C00d3z3ssU/download?ixid=MnwyNzUyNDB8MHwxfHNlYXJjaHw0fHxkZW52ZXJ8ZW58MHx8fHwxNjM2Nzc5NzY2"
            },
            "categories": [],
            "likes": 10,
            "liked_by_user": false,
            "current_user_collections": [],
            "sponsorship": null,
            "topic_submissions": {
                "wallpapers": {
                    "status": "rejected"
                }
            },
            "user": {
                "id": "qOQ1e9l0U_s",
                "updated_at": "2021-11-12T21:19:40-05:00",
                "username": "jakobnoahrosen",
                "name": "Jakob Rosen",
                "first_name": "Jakob",
                "last_name": "Rosen",
                "twitter_username": null,
                "portfolio_url": "https://www.instagram.com/jakobnoahrosen/",
                "bio": null,
                "location": "Denver, Co",
                "links": {
                    "self": "https://api.unsplash.com/users/jakobnoahrosen",
                    "html": "https://unsplash.com/@jakobnoahrosen",
                    "photos": "https://api.unsplash.com/users/jakobnoahrosen/photos",
                    "likes": "https://api.unsplash.com/users/jakobnoahrosen/likes",
                    "portfolio": "https://api.unsplash.com/users/jakobnoahrosen/portfolio",
                    "following": "https://api.unsplash.com/users/jakobnoahrosen/following",
                    "followers": "https://api.unsplash.com/users/jakobnoahrosen/followers"
                },
                "profile_image": {
                    "small": "https://images.unsplash.com/profile-1616187995138-11252f2dd5b2image?ixlib=rb-1.2.1&q=80&fm=jpg&crop=faces&cs=tinysrgb&fit=crop&h=32&w=32",
                    "medium": "https://images.unsplash.com/profile-1616187995138-11252f2dd5b2image?ixlib=rb-1.2.1&q=80&fm=jpg&crop=faces&cs=tinysrgb&fit=crop&h=64&w=64",
                    "large": "https://images.unsplash.com/profile-1616187995138-11252f2dd5b2image?ixlib=rb-1.2.1&q=80&fm=jpg&crop=faces&cs=tinysrgb&fit=crop&h=128&w=128"
                },
                "instagram_username": "jakobnoahrosen",
                "total_collections": 8,
                "total_likes": 108,
                "total_photos": 2433,
                "accepted_tos": true,
                "for_hire": true,
                "social": {
                    "instagram_username": "jakobnoahrosen",
                    "portfolio_url": "https://www.instagram.com/jakobnoahrosen/",
                    "twitter_username": null,
                    "paypal_email": null
                }
            },
            "tags": [
                {
                    "type": "search",
                    "title": "denver"
                },
                {
                    "type": "search",
                    "title": "co"
                },
                {
                    "type": "landing_page",
                    "title": "grey",
                    "source": {
                        "ancestry": {
                            "type": {
                                "slug": "wallpapers",
                                "pretty_slug": "HD Wallpapers"
                            },
                            "category": {
                                "slug": "colors",
                                "pretty_slug": "Color"
                            },
                            "subcategory": {
                                "slug": "grey",
                                "pretty_slug": "Grey"
                            }
                        },
                        "title": "HD Grey Wallpapers",
                        "subtitle": "Download Free Grey Wallpapers",
                        "description": "Choose from a curated selection of grey wallpapers for your mobile and desktop screens. Always free on Unsplash.",
                        "meta_title": "Grey Wallpapers: Free HD Download [500+ HQ] | Unsplash",
                        "meta_description": "Choose from hundreds of free grey wallpapers. Download HD wallpapers for free on Unsplash.",
                        "cover_photo": {
                            "id": "ctXf1GVyf9A",
                            "created_at": "2018-09-10T04:05:55-04:00",
                            "updated_at": "2021-11-11T13:06:10-05:00",
                            "promoted_at": null,
                            "width": 5304,
                            "height": 7952,
                            "color": "#a6a6a6",
                            "blur_hash": "L3IYFNIU00~q-;M{R*t80KtRIUM{",
                            "description": "Old stone background texture",
                            "alt_description": null,
                            "urls": {
                                "raw": "https://images.unsplash.com/photo-1536566482680-fca31930a0bd?ixlib=rb-1.2.1",
                                "full": "https://images.unsplash.com/photo-1536566482680-fca31930a0bd?ixlib=rb-1.2.1&q=85&fm=jpg&crop=entropy&cs=srgb",
                                "regular": "https://images.unsplash.com/photo-1536566482680-fca31930a0bd?ixlib=rb-1.2.1&q=80&fm=jpg&crop=entropy&cs=tinysrgb&w=1080&fit=max",
                                "small": "https://images.unsplash.com/photo-1536566482680-fca31930a0bd?ixlib=rb-1.2.1&q=80&fm=jpg&crop=entropy&cs=tinysrgb&w=400&fit=max",
                                "thumb": "https://images.unsplash.com/photo-1536566482680-fca31930a0bd?ixlib=rb-1.2.1&q=80&fm=jpg&crop=entropy&cs=tinysrgb&w=200&fit=max"
                            },
                            "links": {
                                "self": "https://api.unsplash.com/photos/ctXf1GVyf9A",
                                "html": "https://unsplash.com/photos/ctXf1GVyf9A",
                                "download": "https://unsplash.com/photos/ctXf1GVyf9A/download",
                                "download_location": "https://api.unsplash.com/photos/ctXf1GVyf9A/download"
                            },
                            "categories": [],
                            "likes": 1179,
                            "liked_by_user": false,
                            "current_user_collections": [],
                            "sponsorship": null,
                            "topic_submissions": {
                                "textures-patterns": {
                                    "status": "approved",
                                    "approved_on": "2020-04-06T10:20:11-04:00"
                                }
                            },
                            "user": {
                                "id": "IFcEhJqem0Q",
                                "updated_at": "2021-11-12T04:19:02-05:00",
                                "username": "anniespratt",
                                "name": "Annie Spratt",
                                "first_name": "Annie",
                                "last_name": "Spratt",
                                "twitter_username": "anniespratt",
                                "portfolio_url": "https://anniespratt.com",
                                "bio": "Hobbyist photographer from England, sharing my digital, film + vintage slide scans.  \r\nClick 'Collections' to view my photos in handy folders 😀  Prints 👉🏻 anniespratt.con",
                                "location": "New Forest National Park, UK",
                                "links": {
                                    "self": "https://api.unsplash.com/users/anniespratt",
                                    "html": "https://unsplash.com/@anniespratt",
                                    "photos": "https://api.unsplash.com/users/anniespratt/photos",
                                    "likes": "https://api.unsplash.com/users/anniespratt/likes",
                                    "portfolio": "https://api.unsplash.com/users/anniespratt/portfolio",
                                    "following": "https://api.unsplash.com/users/anniespratt/following",
                                    "followers": "https://api.unsplash.com/users/anniespratt/followers"
                                },
                                "profile_image": {
                                    "small": "https://images.unsplash.com/profile-1628142977790-d9f66dcbc498image?ixlib=rb-1.2.1&q=80&fm=jpg&crop=faces&cs=tinysrgb&fit=crop&h=32&w=32",
                                    "medium": "https://images.unsplash.com/profile-1628142977790-d9f66dcbc498image?ixlib=rb-1.2.1&q=80&fm=jpg&crop=faces&cs=tinysrgb&fit=crop&h=64&w=64",
                                    "large": "https://images.unsplash.com/profile-1628142977790-d9f66dcbc498image?ixlib=rb-1.2.1&q=80&fm=jpg&crop=faces&cs=tinysrgb&fit=crop&h=128&w=128"
                                },
                                "instagram_username": "anniespratt",
                                "total_collections": 141,
                                "total_likes": 14245,
                                "total_photos": 14146,
                                "accepted_tos": true,
                                "for_hire": false,
                                "social": {
                                    "instagram_username": "anniespratt",
                                    "portfolio_url": "https://anniespratt.com",
                                    "twitter_username": "anniespratt",
                                    "paypal_email": null
                                }
                            }
                        }
                    }
                }
            ]
        },
        {
            "id": "ud0Y1ItHhr0",
            "created_at": "2020-04-12T21:08:30-04:00",
            "updated_at": "2021-11-12T07:16:58-05:00",
            "promoted_at": null,
            "width": 5469,
            "height": 3646,
            "color": "#737373",
            "blur_hash": "LDHxgDJCAd]}xgGIOX%1%QNFNK$%",
            "description": "Downtown Denver West Golden Hour 20190907",
            "alt_description": "high rise buildings under white clouds and blue sky during daytime",
            "urls": {
                "raw": "https://images.unsplash.com/photo-1586740070162-41777c99457f?ixid=MnwyNzUyNDB8MHwxfHNlYXJjaHw1fHxkZW52ZXJ8ZW58MHx8fHwxNjM2Nzc5NzY2&ixlib=rb-1.2.1",
                "full": "https://images.unsplash.com/photo-1586740070162-41777c99457f?crop=entropy&cs=srgb&fm=jpg&ixid=MnwyNzUyNDB8MHwxfHNlYXJjaHw1fHxkZW52ZXJ8ZW58MHx8fHwxNjM2Nzc5NzY2&ixlib=rb-1.2.1&q=85",
                "regular": "https://images.unsplash.com/photo-1586740070162-41777c99457f?crop=entropy&cs=tinysrgb&fit=max&fm=jpg&ixid=MnwyNzUyNDB8MHwxfHNlYXJjaHw1fHxkZW52ZXJ8ZW58MHx8fHwxNjM2Nzc5NzY2&ixlib=rb-1.2.1&q=80&w=1080",
                "small": "https://images.unsplash.com/photo-1586740070162-41777c99457f?crop=entropy&cs=tinysrgb&fit=max&fm=jpg&ixid=MnwyNzUyNDB8MHwxfHNlYXJjaHw1fHxkZW52ZXJ8ZW58MHx8fHwxNjM2Nzc5NzY2&ixlib=rb-1.2.1&q=80&w=400",
                "thumb": "https://images.unsplash.com/photo-1586740070162-41777c99457f?crop=entropy&cs=tinysrgb&fit=max&fm=jpg&ixid=MnwyNzUyNDB8MHwxfHNlYXJjaHw1fHxkZW52ZXJ8ZW58MHx8fHwxNjM2Nzc5NzY2&ixlib=rb-1.2.1&q=80&w=200"
            },
            "links": {
                "self": "https://api.unsplash.com/photos/ud0Y1ItHhr0",
                "html": "https://unsplash.com/photos/ud0Y1ItHhr0",
                "download": "https://unsplash.com/photos/ud0Y1ItHhr0/download?ixid=MnwyNzUyNDB8MHwxfHNlYXJjaHw1fHxkZW52ZXJ8ZW58MHx8fHwxNjM2Nzc5NzY2",
                "download_location": "https://api.unsplash.com/photos/ud0Y1ItHhr0/download?ixid=MnwyNzUyNDB8MHwxfHNlYXJjaHw1fHxkZW52ZXJ8ZW58MHx8fHwxNjM2Nzc5NzY2"
            },
            "categories": [],
            "likes": 77,
            "liked_by_user": false,
            "current_user_collections": [],
            "sponsorship": null,
            "topic_submissions": {},
            "user": {
                "id": "iReUjmhpLcw",
                "updated_at": "2021-11-12T08:29:10-05:00",
                "username": "andrewcoop",
                "name": "Andrew Coop",
                "first_name": "Andrew",
                "last_name": "Coop",
                "twitter_username": null,
                "portfolio_url": null,
                "bio": "I'm an amateur who likes to shoot just about everything that looks interesting.  I want to get more experience with portraiture, and will shoot personal photos for anyone for free.  Where possible, attribution is appreciated please and thank you.",
                "location": "Aurora, CO, USA",
                "links": {
                    "self": "https://api.unsplash.com/users/andrewcoop",
                    "html": "https://unsplash.com/@andrewcoop",
                    "photos": "https://api.unsplash.com/users/andrewcoop/photos",
                    "likes": "https://api.unsplash.com/users/andrewcoop/likes",
                    "portfolio": "https://api.unsplash.com/users/andrewcoop/portfolio",
                    "following": "https://api.unsplash.com/users/andrewcoop/following",
                    "followers": "https://api.unsplash.com/users/andrewcoop/followers"
                },
                "profile_image": {
                    "small": "https://images.unsplash.com/profile-1623106766393-2f16aecfe7b9image?ixlib=rb-1.2.1&q=80&fm=jpg&crop=faces&cs=tinysrgb&fit=crop&h=32&w=32",
                    "medium": "https://images.unsplash.com/profile-1623106766393-2f16aecfe7b9image?ixlib=rb-1.2.1&q=80&fm=jpg&crop=faces&cs=tinysrgb&fit=crop&h=64&w=64",
                    "large": "https://images.unsplash.com/profile-1623106766393-2f16aecfe7b9image?ixlib=rb-1.2.1&q=80&fm=jpg&crop=faces&cs=tinysrgb&fit=crop&h=128&w=128"
                },
                "instagram_username": null,
                "total_collections": 0,
                "total_likes": 36,
                "total_photos": 296,
                "accepted_tos": true,
                "for_hire": true,
                "social": {
                    "instagram_username": null,
                    "portfolio_url": null,
                    "twitter_username": null,
                    "paypal_email": null
                }
            },
            "tags": [
                {
                    "type": "search",
                    "title": "denver"
                },
                {
                    "type": "search",
                    "title": "co"
                },
                {
                    "type": "search",
                    "title": "usa"
                }
            ]
        },
        {
            "id": "iiH1dRhldPc",
            "created_at": "2021-03-31T23:14:03-04:00",
            "updated_at": "2021-11-12T20:25:52-05:00",
            "promoted_at": "2021-04-01T08:00:01-04:00",
            "width": 3967,
            "height": 5770,
            "color": "#597373",
            "blur_hash": "LPEorcEL-oNG?^xZWWofkqIVt6j[",
            "description": null,
            "alt_description": "aerial view of city buildings during daytime",
            "urls": {
                "raw": "https://images.unsplash.com/photo-1617246405400-462cb1ab98ab?ixid=MnwyNzUyNDB8MHwxfHNlYXJjaHw2fHxkZW52ZXJ8ZW58MHx8fHwxNjM2Nzc5NzY2&ixlib=rb-1.2.1",
                "full": "https://images.unsplash.com/photo-1617246405400-462cb1ab98ab?crop=entropy&cs=srgb&fm=jpg&ixid=MnwyNzUyNDB8MHwxfHNlYXJjaHw2fHxkZW52ZXJ8ZW58MHx8fHwxNjM2Nzc5NzY2&ixlib=rb-1.2.1&q=85",
                "regular": "https://images.unsplash.com/photo-1617246405400-462cb1ab98ab?crop=entropy&cs=tinysrgb&fit=max&fm=jpg&ixid=MnwyNzUyNDB8MHwxfHNlYXJjaHw2fHxkZW52ZXJ8ZW58MHx8fHwxNjM2Nzc5NzY2&ixlib=rb-1.2.1&q=80&w=1080",
                "small": "https://images.unsplash.com/photo-1617246405400-462cb1ab98ab?crop=entropy&cs=tinysrgb&fit=max&fm=jpg&ixid=MnwyNzUyNDB8MHwxfHNlYXJjaHw2fHxkZW52ZXJ8ZW58MHx8fHwxNjM2Nzc5NzY2&ixlib=rb-1.2.1&q=80&w=400",
                "thumb": "https://images.unsplash.com/photo-1617246405400-462cb1ab98ab?crop=entropy&cs=tinysrgb&fit=max&fm=jpg&ixid=MnwyNzUyNDB8MHwxfHNlYXJjaHw2fHxkZW52ZXJ8ZW58MHx8fHwxNjM2Nzc5NzY2&ixlib=rb-1.2.1&q=80&w=200"
            },
            "links": {
                "self": "https://api.unsplash.com/photos/iiH1dRhldPc",
                "html": "https://unsplash.com/photos/iiH1dRhldPc",
                "download": "https://unsplash.com/photos/iiH1dRhldPc/download?ixid=MnwyNzUyNDB8MHwxfHNlYXJjaHw2fHxkZW52ZXJ8ZW58MHx8fHwxNjM2Nzc5NzY2",
                "download_location": "https://api.unsplash.com/photos/iiH1dRhldPc/download?ixid=MnwyNzUyNDB8MHwxfHNlYXJjaHw2fHxkZW52ZXJ8ZW58MHx8fHwxNjM2Nzc5NzY2"
            },
            "categories": [],
            "likes": 122,
            "liked_by_user": false,
            "current_user_collections": [],
            "sponsorship": null,
            "topic_submissions": {},
            "user": {
                "id": "B1TepQxEajg",
                "updated_at": "2021-11-12T23:44:45-05:00",
                "username": "onthesearchforpineapples",
                "name": "Colin Lloyd",
                "first_name": "Colin",
                "last_name": "Lloyd",
                "twitter_username": "otsfpineapples",
                "portfolio_url": "https://cplloyd95.wixsite.com/otsfp",
                "bio": null,
                "location": "Denver, Colorado",
                "links": {
                    "self": "https://api.unsplash.com/users/onthesearchforpineapples",
                    "html": "https://unsplash.com/@onthesearchforpineapples",
                    "photos": "https://api.unsplash.com/users/onthesearchforpineapples/photos",
                    "likes": "https://api.unsplash.com/users/onthesearchforpineapples/likes",
                    "portfolio": "https://api.unsplash.com/users/onthesearchforpineapples/portfolio",
                    "following": "https://api.unsplash.com/users/onthesearchforpineapples/following",
                    "followers": "https://api.unsplash.com/users/onthesearchforpineapples/followers"
                },
                "profile_image": {
                    "small": "https://images.unsplash.com/profile-1616687073587-63950dc1079cimage?ixlib=rb-1.2.1&q=80&fm=jpg&crop=faces&cs=tinysrgb&fit=crop&h=32&w=32",
                    "medium": "https://images.unsplash.com/profile-1616687073587-63950dc1079cimage?ixlib=rb-1.2.1&q=80&fm=jpg&crop=faces&cs=tinysrgb&fit=crop&h=64&w=64",
                    "large": "https://images.unsplash.com/profile-1616687073587-63950dc1079cimage?ixlib=rb-1.2.1&q=80&fm=jpg&crop=faces&cs=tinysrgb&fit=crop&h=128&w=128"
                },
                "instagram_username": "onthesearchforpineapples",
                "total_collections": 0,
                "total_likes": 87,
                "total_photos": 734,
                "accepted_tos": true,
                "for_hire": true,
                "social": {
                    "instagram_username": "onthesearchforpineapples",
                    "portfolio_url": "https://cplloyd95.wixsite.com/otsfp",
                    "twitter_username": "otsfpineapples",
                    "paypal_email": null
                }
            },
            "tags": [
                {
                    "type": "search",
                    "title": "denver"
                },
                {
                    "type": "search",
                    "title": "co"
                },
                {
                    "type": "search",
                    "title": "usa"
                }
            ]
        },
        {
            "id": "1K-rIfCj7CY",
            "created_at": "2020-01-03T09:52:03-05:00",
            "updated_at": "2021-11-12T04:12:51-05:00",
            "promoted_at": null,
            "width": 7436,
            "height": 3726,
            "color": "#262626",
            "blur_hash": "LGD]*h5q$ijZy?%2IoxEAcW=%2t7",
            "description": null,
            "alt_description": "body of water under cloudy sky",
            "urls": {
                "raw": "https://images.unsplash.com/photo-1578062982426-fe3fbb719669?ixid=MnwyNzUyNDB8MHwxfHNlYXJjaHw3fHxkZW52ZXJ8ZW58MHx8fHwxNjM2Nzc5NzY2&ixlib=rb-1.2.1",
                "full": "https://images.unsplash.com/photo-1578062982426-fe3fbb719669?crop=entropy&cs=srgb&fm=jpg&ixid=MnwyNzUyNDB8MHwxfHNlYXJjaHw3fHxkZW52ZXJ8ZW58MHx8fHwxNjM2Nzc5NzY2&ixlib=rb-1.2.1&q=85",
                "regular": "https://images.unsplash.com/photo-1578062982426-fe3fbb719669?crop=entropy&cs=tinysrgb&fit=max&fm=jpg&ixid=MnwyNzUyNDB8MHwxfHNlYXJjaHw3fHxkZW52ZXJ8ZW58MHx8fHwxNjM2Nzc5NzY2&ixlib=rb-1.2.1&q=80&w=1080",
                "small": "https://images.unsplash.com/photo-1578062982426-fe3fbb719669?crop=entropy&cs=tinysrgb&fit=max&fm=jpg&ixid=MnwyNzUyNDB8MHwxfHNlYXJjaHw3fHxkZW52ZXJ8ZW58MHx8fHwxNjM2Nzc5NzY2&ixlib=rb-1.2.1&q=80&w=400",
                "thumb": "https://images.unsplash.com/photo-1578062982426-fe3fbb719669?crop=entropy&cs=tinysrgb&fit=max&fm=jpg&ixid=MnwyNzUyNDB8MHwxfHNlYXJjaHw3fHxkZW52ZXJ8ZW58MHx8fHwxNjM2Nzc5NzY2&ixlib=rb-1.2.1&q=80&w=200"
            },
            "links": {
                "self": "https://api.unsplash.com/photos/1K-rIfCj7CY",
                "html": "https://unsplash.com/photos/1K-rIfCj7CY",
                "download": "https://unsplash.com/photos/1K-rIfCj7CY/download?ixid=MnwyNzUyNDB8MHwxfHNlYXJjaHw3fHxkZW52ZXJ8ZW58MHx8fHwxNjM2Nzc5NzY2",
                "download_location": "https://api.unsplash.com/photos/1K-rIfCj7CY/download?ixid=MnwyNzUyNDB8MHwxfHNlYXJjaHw3fHxkZW52ZXJ8ZW58MHx8fHwxNjM2Nzc5NzY2"
            },
            "categories": [],
            "likes": 38,
            "liked_by_user": false,
            "current_user_collections": [],
            "sponsorship": null,
            "topic_submissions": {},
            "user": {
                "id": "Mxwd0Js1C4E",
                "updated_at": "2021-11-10T02:01:11-05:00",
                "username": "dsignosaur",
                "name": "Devonshire",
                "first_name": "Devonshire",
                "last_name": null,
                "twitter_username": "dsignosaur",
                "portfolio_url": "http://www.designs-db.com/",
                "bio": "IG: @dsignosaur",
                "location": "Frederick, MD",
                "links": {
                    "self": "https://api.unsplash.com/users/dsignosaur",
                    "html": "https://unsplash.com/@dsignosaur",
                    "photos": "https://api.unsplash.com/users/dsignosaur/photos",
                    "likes": "https://api.unsplash.com/users/dsignosaur/likes",
                    "portfolio": "https://api.unsplash.com/users/dsignosaur/portfolio",
                    "following": "https://api.unsplash.com/users/dsignosaur/following",
                    "followers": "https://api.unsplash.com/users/dsignosaur/followers"
                },
                "profile_image": {
                    "small": "https://images.unsplash.com/profile-1617287538773-8cab190a0cbbimage?ixlib=rb-1.2.1&q=80&fm=jpg&crop=faces&cs=tinysrgb&fit=crop&h=32&w=32",
                    "medium": "https://images.unsplash.com/profile-1617287538773-8cab190a0cbbimage?ixlib=rb-1.2.1&q=80&fm=jpg&crop=faces&cs=tinysrgb&fit=crop&h=64&w=64",
                    "large": "https://images.unsplash.com/profile-1617287538773-8cab190a0cbbimage?ixlib=rb-1.2.1&q=80&fm=jpg&crop=faces&cs=tinysrgb&fit=crop&h=128&w=128"
                },
                "instagram_username": "dsignosaur",
                "total_collections": 1,
                "total_likes": 16,
                "total_photos": 41,
                "accepted_tos": true,
                "for_hire": false,
                "social": {
                    "instagram_username": "dsignosaur",
                    "portfolio_url": "http://www.designs-db.com/",
                    "twitter_username": "dsignosaur",
                    "paypal_email": null
                }
            },
            "tags": [
                {
                    "type": "search",
                    "title": "denver"
                },
                {
                    "type": "search",
                    "title": "co"
                },
                {
                    "type": "search",
                    "title": "usa"
                }
            ]
        },
        {
            "id": "tjoxkIODoCE",
            "created_at": "2018-12-30T03:02:24-05:00",
            "updated_at": "2021-11-12T14:06:54-05:00",
            "promoted_at": null,
            "width": 5472,
            "height": 3648,
            "color": "#d9f3f3",
            "blur_hash": "L~I~PxxsoKkCyZt5oLoLNIofa|ax",
            "description": null,
            "alt_description": "aerial photo of city",
            "urls": {
                "raw": "https://images.unsplash.com/photo-1546156929-a4c0ac411f47?ixid=MnwyNzUyNDB8MHwxfHNlYXJjaHw4fHxkZW52ZXJ8ZW58MHx8fHwxNjM2Nzc5NzY2&ixlib=rb-1.2.1",
                "full": "https://images.unsplash.com/photo-1546156929-a4c0ac411f47?crop=entropy&cs=srgb&fm=jpg&ixid=MnwyNzUyNDB8MHwxfHNlYXJjaHw4fHxkZW52ZXJ8ZW58MHx8fHwxNjM2Nzc5NzY2&ixlib=rb-1.2.1&q=85",
                "regular": "https://images.unsplash.com/photo-1546156929-a4c0ac411f47?crop=entropy&cs=tinysrgb&fit=max&fm=jpg&ixid=MnwyNzUyNDB8MHwxfHNlYXJjaHw4fHxkZW52ZXJ8ZW58MHx8fHwxNjM2Nzc5NzY2&ixlib=rb-1.2.1&q=80&w=1080",
                "small": "https://images.unsplash.com/photo-1546156929-a4c0ac411f47?crop=entropy&cs=tinysrgb&fit=max&fm=jpg&ixid=MnwyNzUyNDB8MHwxfHNlYXJjaHw4fHxkZW52ZXJ8ZW58MHx8fHwxNjM2Nzc5NzY2&ixlib=rb-1.2.1&q=80&w=400",
                "thumb": "https://images.unsplash.com/photo-1546156929-a4c0ac411f47?crop=entropy&cs=tinysrgb&fit=max&fm=jpg&ixid=MnwyNzUyNDB8MHwxfHNlYXJjaHw4fHxkZW52ZXJ8ZW58MHx8fHwxNjM2Nzc5NzY2&ixlib=rb-1.2.1&q=80&w=200"
            },
            "links": {
                "self": "https://api.unsplash.com/photos/tjoxkIODoCE",
                "html": "https://unsplash.com/photos/tjoxkIODoCE",
                "download": "https://unsplash.com/photos/tjoxkIODoCE/download?ixid=MnwyNzUyNDB8MHwxfHNlYXJjaHw4fHxkZW52ZXJ8ZW58MHx8fHwxNjM2Nzc5NzY2",
                "download_location": "https://api.unsplash.com/photos/tjoxkIODoCE/download?ixid=MnwyNzUyNDB8MHwxfHNlYXJjaHw4fHxkZW52ZXJ8ZW58MHx8fHwxNjM2Nzc5NzY2"
            },
            "categories": [],
            "likes": 93,
            "liked_by_user": false,
            "current_user_collections": [],
            "sponsorship": null,
            "topic_submissions": {},
            "user": {
                "id": "3NS5bv8kZU4",
                "updated_at": "2021-11-10T05:59:21-05:00",
                "username": "theadventurebitch",
                "name": "Cassie Gallegos",
                "first_name": "Cassie",
                "last_name": "Gallegos",
                "twitter_username": "adventure_bitch",
                "portfolio_url": "https://shor.by/YtNY",
                "bio": "Adventurer + Philosopher + Entrepreneur + Financial Badass ",
                "location": "Denver, CO",
                "links": {
                    "self": "https://api.unsplash.com/users/theadventurebitch",
                    "html": "https://unsplash.com/@theadventurebitch",
                    "photos": "https://api.unsplash.com/users/theadventurebitch/photos",
                    "likes": "https://api.unsplash.com/users/theadventurebitch/likes",
                    "portfolio": "https://api.unsplash.com/users/theadventurebitch/portfolio",
                    "following": "https://api.unsplash.com/users/theadventurebitch/following",
                    "followers": "https://api.unsplash.com/users/theadventurebitch/followers"
                },
                "profile_image": {
                    "small": "https://images.unsplash.com/profile-1602182906260-56de50acab65image?ixlib=rb-1.2.1&q=80&fm=jpg&crop=faces&cs=tinysrgb&fit=crop&h=32&w=32",
                    "medium": "https://images.unsplash.com/profile-1602182906260-56de50acab65image?ixlib=rb-1.2.1&q=80&fm=jpg&crop=faces&cs=tinysrgb&fit=crop&h=64&w=64",
                    "large": "https://images.unsplash.com/profile-1602182906260-56de50acab65image?ixlib=rb-1.2.1&q=80&fm=jpg&crop=faces&cs=tinysrgb&fit=crop&h=128&w=128"
                },
                "instagram_username": "Theadventurebitch",
                "total_collections": 9,
                "total_likes": 6,
                "total_photos": 30,
                "accepted_tos": true,
                "for_hire": true,
                "social": {
                    "instagram_username": "Theadventurebitch",
                    "portfolio_url": "https://shor.by/YtNY",
                    "twitter_username": "adventure_bitch",
                    "paypal_email": null
                }
            },
            "tags": [
                {
                    "type": "search",
                    "title": "denver"
                },
                {
                    "type": "search",
                    "title": "colorado"
                },
                {
                    "type": "search",
                    "title": "city park"
                }
            ]
        },
        {
            "id": "timxolFiGqk",
            "created_at": "2021-04-02T12:13:52-04:00",
            "updated_at": "2021-11-12T20:25:55-05:00",
            "promoted_at": "2021-04-03T06:54:02-04:00",
            "width": 4032,
            "height": 3024,
            "color": "#a6c0d9",
            "blur_hash": "LsGJ8DoyRkj[*0WCofaztRayRjof",
            "description": "instagram - @jakobnoahrosen",
            "alt_description": "high rise buildings during daytime",
            "urls": {
                "raw": "https://images.unsplash.com/photo-1617379773512-4bb1ad9349cf?ixid=MnwyNzUyNDB8MHwxfHNlYXJjaHw5fHxkZW52ZXJ8ZW58MHx8fHwxNjM2Nzc5NzY2&ixlib=rb-1.2.1",
                "full": "https://images.unsplash.com/photo-1617379773512-4bb1ad9349cf?crop=entropy&cs=srgb&fm=jpg&ixid=MnwyNzUyNDB8MHwxfHNlYXJjaHw5fHxkZW52ZXJ8ZW58MHx8fHwxNjM2Nzc5NzY2&ixlib=rb-1.2.1&q=85",
                "regular": "https://images.unsplash.com/photo-1617379773512-4bb1ad9349cf?crop=entropy&cs=tinysrgb&fit=max&fm=jpg&ixid=MnwyNzUyNDB8MHwxfHNlYXJjaHw5fHxkZW52ZXJ8ZW58MHx8fHwxNjM2Nzc5NzY2&ixlib=rb-1.2.1&q=80&w=1080",
                "small": "https://images.unsplash.com/photo-1617379773512-4bb1ad9349cf?crop=entropy&cs=tinysrgb&fit=max&fm=jpg&ixid=MnwyNzUyNDB8MHwxfHNlYXJjaHw5fHxkZW52ZXJ8ZW58MHx8fHwxNjM2Nzc5NzY2&ixlib=rb-1.2.1&q=80&w=400",
                "thumb": "https://images.unsplash.com/photo-1617379773512-4bb1ad9349cf?crop=entropy&cs=tinysrgb&fit=max&fm=jpg&ixid=MnwyNzUyNDB8MHwxfHNlYXJjaHw5fHxkZW52ZXJ8ZW58MHx8fHwxNjM2Nzc5NzY2&ixlib=rb-1.2.1&q=80&w=200"
            },
            "links": {
                "self": "https://api.unsplash.com/photos/timxolFiGqk",
                "html": "https://unsplash.com/photos/timxolFiGqk",
                "download": "https://unsplash.com/photos/timxolFiGqk/download?ixid=MnwyNzUyNDB8MHwxfHNlYXJjaHw5fHxkZW52ZXJ8ZW58MHx8fHwxNjM2Nzc5NzY2",
                "download_location": "https://api.unsplash.com/photos/timxolFiGqk/download?ixid=MnwyNzUyNDB8MHwxfHNlYXJjaHw5fHxkZW52ZXJ8ZW58MHx8fHwxNjM2Nzc5NzY2"
            },
            "categories": [],
            "likes": 25,
            "liked_by_user": false,
            "current_user_collections": [],
            "sponsorship": null,
            "topic_submissions": {},
            "user": {
                "id": "qOQ1e9l0U_s",
                "updated_at": "2021-11-12T21:19:40-05:00",
                "username": "jakobnoahrosen",
                "name": "Jakob Rosen",
                "first_name": "Jakob",
                "last_name": "Rosen",
                "twitter_username": null,
                "portfolio_url": "https://www.instagram.com/jakobnoahrosen/",
                "bio": null,
                "location": "Denver, Co",
                "links": {
                    "self": "https://api.unsplash.com/users/jakobnoahrosen",
                    "html": "https://unsplash.com/@jakobnoahrosen",
                    "photos": "https://api.unsplash.com/users/jakobnoahrosen/photos",
                    "likes": "https://api.unsplash.com/users/jakobnoahrosen/likes",
                    "portfolio": "https://api.unsplash.com/users/jakobnoahrosen/portfolio",
                    "following": "https://api.unsplash.com/users/jakobnoahrosen/following",
                    "followers": "https://api.unsplash.com/users/jakobnoahrosen/followers"
                },
                "profile_image": {
                    "small": "https://images.unsplash.com/profile-1616187995138-11252f2dd5b2image?ixlib=rb-1.2.1&q=80&fm=jpg&crop=faces&cs=tinysrgb&fit=crop&h=32&w=32",
                    "medium": "https://images.unsplash.com/profile-1616187995138-11252f2dd5b2image?ixlib=rb-1.2.1&q=80&fm=jpg&crop=faces&cs=tinysrgb&fit=crop&h=64&w=64",
                    "large": "https://images.unsplash.com/profile-1616187995138-11252f2dd5b2image?ixlib=rb-1.2.1&q=80&fm=jpg&crop=faces&cs=tinysrgb&fit=crop&h=128&w=128"
                },
                "instagram_username": "jakobnoahrosen",
                "total_collections": 8,
                "total_likes": 108,
                "total_photos": 2433,
                "accepted_tos": true,
                "for_hire": true,
                "social": {
                    "instagram_username": "jakobnoahrosen",
                    "portfolio_url": "https://www.instagram.com/jakobnoahrosen/",
                    "twitter_username": null,
                    "paypal_email": null
                }
            },
            "tags": [
                {
                    "type": "search",
                    "title": "denver"
                },
                {
                    "type": "search",
                    "title": "colorado rockies"
                },
                {
                    "type": "search",
                    "title": "denver co"
                }
            ]
        },
        {
            "id": "chaqHXlOzYs",
            "created_at": "2018-02-23T17:18:23-05:00",
            "updated_at": "2021-11-12T11:03:48-05:00",
            "promoted_at": null,
            "width": 6000,
            "height": 4000,
            "color": "#0c2626",
            "blur_hash": "LRCP|u9F9F%M~qD%IUx]-;MxWBof",
            "description": "Walking the streets of downtown Denver on a foggy, freezing cold day.",
            "alt_description": "woman walking on street near SUV during daytime",
            "urls": {
                "raw": "https://images.unsplash.com/photo-1519424187720-db6d0fc5a5d2?ixid=MnwyNzUyNDB8MHwxfHNlYXJjaHwxMHx8ZGVudmVyfGVufDB8fHx8MTYzNjc3OTc2Ng&ixlib=rb-1.2.1",
                "full": "https://images.unsplash.com/photo-1519424187720-db6d0fc5a5d2?crop=entropy&cs=srgb&fm=jpg&ixid=MnwyNzUyNDB8MHwxfHNlYXJjaHwxMHx8ZGVudmVyfGVufDB8fHx8MTYzNjc3OTc2Ng&ixlib=rb-1.2.1&q=85",
                "regular": "https://images.unsplash.com/photo-1519424187720-db6d0fc5a5d2?crop=entropy&cs=tinysrgb&fit=max&fm=jpg&ixid=MnwyNzUyNDB8MHwxfHNlYXJjaHwxMHx8ZGVudmVyfGVufDB8fHx8MTYzNjc3OTc2Ng&ixlib=rb-1.2.1&q=80&w=1080",
                "small": "https://images.unsplash.com/photo-1519424187720-db6d0fc5a5d2?crop=entropy&cs=tinysrgb&fit=max&fm=jpg&ixid=MnwyNzUyNDB8MHwxfHNlYXJjaHwxMHx8ZGVudmVyfGVufDB8fHx8MTYzNjc3OTc2Ng&ixlib=rb-1.2.1&q=80&w=400",
                "thumb": "https://images.unsplash.com/photo-1519424187720-db6d0fc5a5d2?crop=entropy&cs=tinysrgb&fit=max&fm=jpg&ixid=MnwyNzUyNDB8MHwxfHNlYXJjaHwxMHx8ZGVudmVyfGVufDB8fHx8MTYzNjc3OTc2Ng&ixlib=rb-1.2.1&q=80&w=200"
            },
            "links": {
                "self": "https://api.unsplash.com/photos/chaqHXlOzYs",
                "html": "https://unsplash.com/photos/chaqHXlOzYs",
                "download": "https://unsplash.com/photos/chaqHXlOzYs/download?ixid=MnwyNzUyNDB8MHwxfHNlYXJjaHwxMHx8ZGVudmVyfGVufDB8fHx8MTYzNjc3OTc2Ng",
                "download_location": "https://api.unsplash.com/photos/chaqHXlOzYs/download?ixid=MnwyNzUyNDB8MHwxfHNlYXJjaHwxMHx8ZGVudmVyfGVufDB8fHx8MTYzNjc3OTc2Ng"
            },
            "categories": [],
            "likes": 165,
            "liked_by_user": false,
            "current_user_collections": [],
            "sponsorship": null,
            "topic_submissions": {
                "street-photography": {
                    "status": "rejected"
                }
            },
            "user": {
                "id": "R9wpgxVwO48",
                "updated_at": "2021-11-11T15:18:32-05:00",
                "username": "owencavlys",
                "name": "Owen Lystrup",
                "first_name": "Owen",
                "last_name": "Lystrup",
                "twitter_username": "owen_lystrup",
                "portfolio_url": "https://owenlystrup.com",
                "bio": "Photographer, writer, editor, creative director. \r\n See more of my photography here: instagram.com/@owencavlys/  See my writing here: medium.com/cisco-shifted",
                "location": "Denver, by way of Mojave, San Francisco, and Los Angeles",
                "links": {
                    "self": "https://api.unsplash.com/users/owencavlys",
                    "html": "https://unsplash.com/@owencavlys",
                    "photos": "https://api.unsplash.com/users/owencavlys/photos",
                    "likes": "https://api.unsplash.com/users/owencavlys/likes",
                    "portfolio": "https://api.unsplash.com/users/owencavlys/portfolio",
                    "following": "https://api.unsplash.com/users/owencavlys/following",
                    "followers": "https://api.unsplash.com/users/owencavlys/followers"
                },
                "profile_image": {
                    "small": "https://images.unsplash.com/profile-1497426481273-c0e02f108715?ixlib=rb-1.2.1&q=80&fm=jpg&crop=faces&cs=tinysrgb&fit=crop&h=32&w=32",
                    "medium": "https://images.unsplash.com/profile-1497426481273-c0e02f108715?ixlib=rb-1.2.1&q=80&fm=jpg&crop=faces&cs=tinysrgb&fit=crop&h=64&w=64",
                    "large": "https://images.unsplash.com/profile-1497426481273-c0e02f108715?ixlib=rb-1.2.1&q=80&fm=jpg&crop=faces&cs=tinysrgb&fit=crop&h=128&w=128"
                },
                "instagram_username": "owencavlys",
                "total_collections": 0,
                "total_likes": 188,
                "total_photos": 27,
                "accepted_tos": true,
                "for_hire": true,
                "social": {
                    "instagram_username": "owencavlys",
                    "portfolio_url": "https://owenlystrup.com",
                    "twitter_username": "owen_lystrup",
                    "paypal_email": null
                }
            },
            "tags": [
                {
                    "type": "search",
                    "title": "denver"
                },
                {
                    "type": "landing_page",
                    "title": "grey",
                    "source": {
                        "ancestry": {
                            "type": {
                                "slug": "wallpapers",
                                "pretty_slug": "HD Wallpapers"
                            },
                            "category": {
                                "slug": "colors",
                                "pretty_slug": "Color"
                            },
                            "subcategory": {
                                "slug": "grey",
                                "pretty_slug": "Grey"
                            }
                        },
                        "title": "HD Grey Wallpapers",
                        "subtitle": "Download Free Grey Wallpapers",
                        "description": "Choose from a curated selection of grey wallpapers for your mobile and desktop screens. Always free on Unsplash.",
                        "meta_title": "Grey Wallpapers: Free HD Download [500+ HQ] | Unsplash",
                        "meta_description": "Choose from hundreds of free grey wallpapers. Download HD wallpapers for free on Unsplash.",
                        "cover_photo": {
                            "id": "ctXf1GVyf9A",
                            "created_at": "2018-09-10T04:05:55-04:00",
                            "updated_at": "2021-11-11T13:06:10-05:00",
                            "promoted_at": null,
                            "width": 5304,
                            "height": 7952,
                            "color": "#a6a6a6",
                            "blur_hash": "L3IYFNIU00~q-;M{R*t80KtRIUM{",
                            "description": "Old stone background texture",
                            "alt_description": null,
                            "urls": {
                                "raw": "https://images.unsplash.com/photo-1536566482680-fca31930a0bd?ixlib=rb-1.2.1",
                                "full": "https://images.unsplash.com/photo-1536566482680-fca31930a0bd?ixlib=rb-1.2.1&q=85&fm=jpg&crop=entropy&cs=srgb",
                                "regular": "https://images.unsplash.com/photo-1536566482680-fca31930a0bd?ixlib=rb-1.2.1&q=80&fm=jpg&crop=entropy&cs=tinysrgb&w=1080&fit=max",
                                "small": "https://images.unsplash.com/photo-1536566482680-fca31930a0bd?ixlib=rb-1.2.1&q=80&fm=jpg&crop=entropy&cs=tinysrgb&w=400&fit=max",
                                "thumb": "https://images.unsplash.com/photo-1536566482680-fca31930a0bd?ixlib=rb-1.2.1&q=80&fm=jpg&crop=entropy&cs=tinysrgb&w=200&fit=max"
                            },
                            "links": {
                                "self": "https://api.unsplash.com/photos/ctXf1GVyf9A",
                                "html": "https://unsplash.com/photos/ctXf1GVyf9A",
                                "download": "https://unsplash.com/photos/ctXf1GVyf9A/download",
                                "download_location": "https://api.unsplash.com/photos/ctXf1GVyf9A/download"
                            },
                            "categories": [],
                            "likes": 1179,
                            "liked_by_user": false,
                            "current_user_collections": [],
                            "sponsorship": null,
                            "topic_submissions": {
                                "textures-patterns": {
                                    "status": "approved",
                                    "approved_on": "2020-04-06T10:20:11-04:00"
                                }
                            },
                            "user": {
                                "id": "IFcEhJqem0Q",
                                "updated_at": "2021-11-12T04:19:02-05:00",
                                "username": "anniespratt",
                                "name": "Annie Spratt",
                                "first_name": "Annie",
                                "last_name": "Spratt",
                                "twitter_username": "anniespratt",
                                "portfolio_url": "https://anniespratt.com",
                                "bio": "Hobbyist photographer from England, sharing my digital, film + vintage slide scans.  \r\nClick 'Collections' to view my photos in handy folders 😀  Prints 👉🏻 anniespratt.con",
                                "location": "New Forest National Park, UK",
                                "links": {
                                    "self": "https://api.unsplash.com/users/anniespratt",
                                    "html": "https://unsplash.com/@anniespratt",
                                    "photos": "https://api.unsplash.com/users/anniespratt/photos",
                                    "likes": "https://api.unsplash.com/users/anniespratt/likes",
                                    "portfolio": "https://api.unsplash.com/users/anniespratt/portfolio",
                                    "following": "https://api.unsplash.com/users/anniespratt/following",
                                    "followers": "https://api.unsplash.com/users/anniespratt/followers"
                                },
                                "profile_image": {
                                    "small": "https://images.unsplash.com/profile-1628142977790-d9f66dcbc498image?ixlib=rb-1.2.1&q=80&fm=jpg&crop=faces&cs=tinysrgb&fit=crop&h=32&w=32",
                                    "medium": "https://images.unsplash.com/profile-1628142977790-d9f66dcbc498image?ixlib=rb-1.2.1&q=80&fm=jpg&crop=faces&cs=tinysrgb&fit=crop&h=64&w=64",
                                    "large": "https://images.unsplash.com/profile-1628142977790-d9f66dcbc498image?ixlib=rb-1.2.1&q=80&fm=jpg&crop=faces&cs=tinysrgb&fit=crop&h=128&w=128"
                                },
                                "instagram_username": "anniespratt",
                                "total_collections": 141,
                                "total_likes": 14245,
                                "total_photos": 14146,
                                "accepted_tos": true,
                                "for_hire": false,
                                "social": {
                                    "instagram_username": "anniespratt",
                                    "portfolio_url": "https://anniespratt.com",
                                    "twitter_username": "anniespratt",
                                    "paypal_email": null
                                }
                            }
                        }
                    }
                },
                {
                    "type": "search",
                    "title": "united states"
                }
            ]
        }
    ]
}
